stactools/sentinel2/__init__.py
stactools/sentinel2/cog.py
stactools/sentinel2/commands.py
stactools/sentinel2/constants.py
stactools/sentinel2/granule_metadata.py
stactools/sentinel2/mgrs.py
stactools/sentinel2/product_metadata.py
stactools/sentinel2/safe_manifest.py
stactools/sentinel2/stac.py
stactools/sentinel2/tileinfo_metadata.py
stactools/sentinel2/utils.py
stactools_sentinel2-0.8.0.dist-info/licenses/LICENSE
stactools_sentinel2-0.8.0.dist-info/METADATA
stactools_sentinel2-0.8.0.dist-info/WHEEL
stactools_sentinel2-0.8.0.dist-info/top_level.txt
stactools_sentinel2-0.8.0.dist-info/RECORD
