Metadata-Version: 2.4
Name: stactools-sentinel2
Version: 0.8.0
Summary: Create STAC Items from Sentinel-2 metadata
Author-email: stac-utils <stac@radiant.earth>
Project-URL: Url, https://github.com/stactools-sentinel2/stactools-sentinel2
Project-URL: Issues, https://github.com/stactools-sentinel2s/stactools-sentinel2/issues
Project-URL: Github, https://github.com/stactools-sentinel2s/stactools-sentinel2
Project-URL: CHANGELOG, https://github.com/stactools-sentinel2s/stactools-sentinel2/blob/main/CHANGELOG.md
Keywords: stactools,pystac,catalog,STAC
Classifier: Development Status :: 4 - Beta
Classifier: License :: OSI Approved :: Apache Software License
Classifier: Programming Language :: Python :: 3.9
Classifier: Programming Language :: Python :: 3.10
Classifier: Programming Language :: Python :: 3.11
Classifier: Programming Language :: Python :: 3.12
Classifier: Programming Language :: Python :: 3.13
Requires-Python: >=3.9
License-File: LICENSE
Requires-Dist: antimeridian>=0.3.5
Requires-Dist: shapely>=2.0.0
Requires-Dist: stactools>=0.5.2
Requires-Dist: pyproj>=3.5.0
Requires-Dist: pystac>=1.9.0
Provides-Extra: dev
Requires-Dist: codespell; extra == "dev"
Requires-Dist: coverage; extra == "dev"
Requires-Dist: pre-commit; extra == "dev"
Requires-Dist: ruff; extra == "dev"
Requires-Dist: pytest; extra == "dev"
Requires-Dist: pytest-cov; extra == "dev"
Requires-Dist: requests; extra == "dev"
Requires-Dist: pystac>1.12; extra == "dev"
Dynamic: license-file
